pinax/__init__.py
pinax/stripe/__init__.py
pinax/stripe/admin.py
pinax/stripe/apps.py
pinax/stripe/conf.py
pinax/stripe/models.py
pinax/stripe/signals.py
pinax/stripe/urls.py
pinax/stripe/utils.py
pinax/stripe/views.py
pinax/stripe/migrations/0001_initial.py
pinax/stripe/migrations/0002_auto_20211126_1416.py
pinax/stripe/migrations/0003_auto_20211127_0119.py
pinax/stripe/migrations/__init__.py
pinax/stripe/templatetags/__init__.py
pinax/stripe/templatetags/stripe.py
pinax/stripe/tests/__init__.py
pinax/stripe/tests/settings.py
pinax/stripe/tests/test_admin.py
pinax/stripe/tests/test_models.py
pinax/stripe/tests/test_signals.py
pinax/stripe/tests/test_templatetags.py
pinax/stripe/tests/test_utils.py
pinax/stripe/tests/test_views.py
pinax/stripe/tests/test_webhooks.py
pinax/stripe/tests/urls.py
pinax/stripe/webhooks/__init__.py
pinax/stripe/webhooks/base.py
pinax/stripe/webhooks/generated.py
pinax/stripe/webhooks/registry.py
pinax_stripe_light-5.0.0.dist-info/AUTHORS
pinax_stripe_light-5.0.0.dist-info/LICENSE
pinax_stripe_light-5.0.0.dist-info/METADATA
pinax_stripe_light-5.0.0.dist-info/WHEEL
pinax_stripe_light-5.0.0.dist-info/top_level.txt
pinax_stripe_light-5.0.0.dist-info/RECORD
