Metadata-Version: 2.1
Name: pinax-stripe-light
Version: 5.0.0
Summary: an app for integrating Stripe into Django
Home-page: https://github.com/pinax/pinax-stripe/
Author: Pinax Team
Author-email: team@pinaxproject.com
License: MIT
Platform: UNKNOWN
Classifier: Development Status :: 5 - Production/Stable
Classifier: Environment :: Web Environment
Classifier: Intended Audience :: Developers
Classifier: License :: OSI Approved :: MIT License
Classifier: Operating System :: OS Independent
Classifier: Programming Language :: Python
Classifier: Programming Language :: Python :: 3
Classifier: Framework :: Django
Classifier: Framework :: Django :: 3.2
Classifier: Topic :: Software Development :: Libraries :: Python Modules
License-File: LICENSE
License-File: AUTHORS
Requires-Dist: django-appconf (>=1.0.1)
Requires-Dist: stripe (>=2.0)
Requires-Dist: django (>=3.2)
Requires-Dist: pytz (>=2021.3)
